wol_api/__init__.py
wol_api/run.py
wol_api/providers/__init__.py
wol_api/providers/shared_state.py
wol_api/providers/version.py
wol_api-1.0.7.dist-info/LICENSE.md
wol_api-1.0.7.dist-info/METADATA
wol_api-1.0.7.dist-info/WHEEL
wol_api-1.0.7.dist-info/entry_points.txt
wol_api-1.0.7.dist-info/top_level.txt
wol_api-1.0.7.dist-info/RECORD
