Metadata-Version: 2.1
Name: wol-api
Version: 1.0.7
Summary: A simple http interface to send wake on LAN commands.
Home-page: https://github.com/rix1337/WakeOnLAN-API
Author: rix1337
Author-email: 
License: UNKNOWN
Platform: UNKNOWN
Classifier: Programming Language :: Python :: 3
Classifier: License :: OSI Approved :: MIT License
Classifier: Operating System :: OS Independent
License-File: LICENSE.md
Requires-Dist: bottle (==0.12.25)
Requires-Dist: wakeonlan (==3.1.0)
